{
  "id": "BN-BE-MK37",
  "level": 2,
  "level_name": {
    "local": "Mukim",
    "en": "Subdistrict"
  },
  "name": {
    "local": "Mukim Seria",
    "en": "Seria",
    "slug": "seria-bn-be-mk37"
  },
  "code": {
    "id": "BN-BE-MK37",
    "iso": null
  },
  "parent": {
    "id": "BN-BE",
    "level": 1,
    "name": {
      "local": "Belait",
      "en": "Belait",
      "slug": "belait-bn-be"
    }
  },
  "ancestors": [
    {
      "id": "BN-BE",
      "level": 1,
      "name": {
        "local": "Belait",
        "en": "Belait",
        "slug": "belait-bn-be"
      }
    }
  ],
  "children_count": {
    "kampong": 8
  },
  "zip_codes": [],
  "geo": {
    "lat": "4.582",
    "lon": "114.353"
  },
  "metadata": {},
  "source": {}
}